{
  "name": "GoCron",
  "longDescription": "<p> A task scheduler built with Go and Vue.js that allows users to specify recurring jobs via a simple YAML configuration file. The scheduler reads job definitions, executes commands at specified times using cron expressions, and passes in environment variables for each job.</p>",
  "description": "A go based task scheduler with GUI",
  "tags": [
    "cron",
    "gui",
    "open-source",
    "self-hosted",
    "linux"
  ],
  "repository": "https://github.com/flohoss/gocron",
  "image": "https://ghcr.io/flohoss/gocron",
  "supported_architectures": [
    "amd64",
    "arm64"
  ]
}
